LICENSE
MANIFEST.in
README.md
setup.py
tests/__init__.py
tests/test_checks.py
tests/test_hk_errors.py
tests/test_oneside_hansonkoopmans.py
tests/test_oneside_hansonkoopmans_cmh.py
tests/test_oneside_lognormal.py
tests/test_oneside_nonparmetric.py
tests/test_oneside_normal.py
tests/test_twoside_lognormal.py
tests/test_twoside_normal.py
tests/test_twoside_normal_factor_iso.py
tests/test_twoside_normal_factor_mhe.py
toleranceinterval/VERSION
toleranceinterval/__init__.py
toleranceinterval/checks.py
toleranceinterval/hk.py
toleranceinterval.egg-info/PKG-INFO
toleranceinterval.egg-info/SOURCES.txt
toleranceinterval.egg-info/dependency_links.txt
toleranceinterval.egg-info/requires.txt
toleranceinterval.egg-info/top_level.txt
toleranceinterval/oneside/__init__.py
toleranceinterval/oneside/oneside.py
toleranceinterval/twoside/__init__.py
toleranceinterval/twoside/_normal_approx.py
toleranceinterval/twoside/_normal_exact.py
toleranceinterval/twoside/twoside.py