Metadata-Version: 2.1
Name: toleranceinterval
Version: 1.0.3
Summary: A small Python library for one-sided tolerance bounds and two-sided tolerance intervals.
Home-page: https://github.com/cjekel/tolerance_interval_py
Author: Charles Jekel
Author-email: cjekel@gmail.com
License: MIT License
Platform: any
Requires-Python: >3.5
License-File: LICENSE
